modules/__init__.py
modules/barcode_trimmer.py
modules/cluster.py
modules/consensus.py
modules/get_sorted_fastq_for_cluster.py
modules/help_functions.py
modules/p_minimizers_shared.py
modules/parallelize.py
ngspeciesid-0.3.1.data/scripts/NGSpeciesID
ngspeciesid-0.3.1.dist-info/licenses/LICENSE.txt
ngspeciesid-0.3.1.dist-info/METADATA
ngspeciesid-0.3.1.dist-info/WHEEL
ngspeciesid-0.3.1.dist-info/top_level.txt
ngspeciesid-0.3.1.dist-info/RECORD
