Metadata-Version: 2.4
Name: NGSpeciesID
Version: 0.3.1
Summary: Reconstructs viral consensus sequences from a set of ONT reads.
Home-page: https://github.com/ksahlin/NGSpeciesID
Author: Kristoffer Sahlin
Author-email: ksahlin@math.su.se
Keywords: viral sequeces ONT Oxford Nanopore Technologies long reads
Classifier: Development Status :: 3 - Alpha
Classifier: Programming Language :: Python :: 3
Classifier: Programming Language :: Python :: 3.4
Classifier: Programming Language :: Python :: 3.5
Classifier: Programming Language :: Python :: 3.6
Classifier: Programming Language :: Python :: 3.7
Requires-Python: !=3.0.*, !=3.1.*, !=3.2.*, !=3.3.*, <4
License-File: LICENSE.txt
Requires-Dist: parasail==1.2.4
Requires-Dist: edlib>=1.1.2
Dynamic: author
Dynamic: author-email
Dynamic: classifier
Dynamic: description
Dynamic: home-page
Dynamic: keywords
Dynamic: license-file
Dynamic: requires-dist
Dynamic: requires-python
Dynamic: summary
